LICENSE
MANIFEST.in
README.md
setup.cfg
setup.py
django_utensils.egg-info/PKG-INFO
django_utensils.egg-info/SOURCES.txt
django_utensils.egg-info/dependency_links.txt
django_utensils.egg-info/not-zip-safe
django_utensils.egg-info/pbr.json
django_utensils.egg-info/requires.txt
django_utensils.egg-info/top_level.txt
example/__init__.py
example/admin.py
example/forms.py
example/manage.py
example/models.py
example/settings.py
example/urls.py
example/views.py
example/wsgi.py
utensils/__init__.py
utensils/context_processors.py
utensils/forms.py
utensils/middleware.py
utensils/models.py
utensils/storage.py
utensils/utils.py
utensils/viewmixins.py
utensils/views.py
utensils/templates/.DS_Store
utensils/templates/utensils/_messages.html
utensils/templates/utensils/_order_by_controls.html
utensils/templates/utensils/_pagination_controls.html
utensils/templates/utensils/_save_cancel_group.html
utensils/templates/utensils/_search.html
utensils/templates/utensils/object_form.html
utensils/templatetags/__init__.py
utensils/templatetags/utensils_tags.py