Metadata-Version: 1.1
Name: django-utensils
Version: 0.2
Summary: Useful Django snippets.
Home-page: https://github.com/code-kitchen/django-utensils/
Author: Ben Tappin
Author-email: ben@mrben.co.uk
License: The MIT License (MIT)
